{
    "insights": [
        {
          "is-insight": true,
          "insights": [
            {"frase": "Cuando tienes hambre no te comportas como tú"},
            {"frase": "El moderneo de los coffees y bakeries ha americanizado nuestro modo de desayunar"},
            {"frase": "Cuando dudamos ante alguna decisión, hacemos un gesto facial"},
            {"frase": "Repetir una palabra para indicar autenticidad"},
            {"frase": "En invierno cualquier rayo de sol activa el mood de verano"},
            {"frase": "En la nevera, al lado de los huevos, guardas el stock sobrante de sobrecitos de Ketchup"},
            {"frase": "Los adultos que no hablan inglés no se enteran de nada"},
            {"frase": "Qué venía a hacer"},
            {"frase": "Taparse la cara cuando te ponen una cámara delante"},
            {"frase": "Las mujeres planifican tareas en el hogar"},
            {"frase": "Eres mi humano"},
            {"frase": "No hacer en la vida lo que realmente quieres o te gusta"},
            {"frase": "Usamos cosas usadas por otros continuamente"},
            {"frase": "Pensar qué te tienes que poner"},
            {"frase": "El agobio del impacto medioambiental de nuestras acciones"},
            {"frase": "La preocupación por el desperdicio alimentario"},
            {"frase": "La preocupación por el plástico en el mar"},
            {"frase": "Las personas mayores no practican sexo"},
            {"frase": "La problemática del consumo de pantallas por parte de la generación alfa"},
            {"frase": "La problemática del bullying"},
            {"frase": "Hacer algo como una niña"},
            {"frase": "Las mujeres pierden la autoestima sana de la niñez"},
            {"frase": "El poder las madres"},
            {"frase": "La necesidad de romper con estereotipos de género desde el hogar"},
            {"frase": "Siempre te ves fea"},
            {"frase": "Los coches no son juguetes para niñas"},
            {"frase": "Las crisis de la adolescencia"},
            {"frase": "Los efectos de lo que cuentan en el cole"},
            {"frase": "El miedo a la reacción de alguien cuando le cuentas algo"},
            {"frase": "El miedo a la aceptación"},
            {"frase": "Hacer lo que te dé la gana, sin pensar en el qué dirán"},
            {"frase": "Siempre vamos corriendo"},
            {"frase": "La España vaciada, cada vez más gente se va de pueblos a ciudades"},
            {"frase": "La sensación de liberación cuando haces deporte"},
            {"frase": "Organizar prioridades en la vida y saber qué es lo más importante"},
            {"frase": "Todas las personas tenemos algo en común"},
            {"frase": "Los regalos que te compra la gente mayor"},
            {"frase": "Las embarazadas no comen jamón"},
            {"frase": "Lucir pelazo produce envidia"},
            {"frase": "No me puedo resistir al soborno"},
            {"frase": "Los chollos que encuentras en los bazares"},
            {"frase": "Los políticos son unos pesados"},
            {"frase": "Sólo puedes pedir paella si vas con alguien"},
            {"frase": "Vivir con entusiasmo y pasión"},
            {"frase": "Los juicios de valor cuando eres madre"},
            {"frase": "Las inseguridades y los prejuicios que tienen que sufrir las mujeres"},
            {"frase": "Los vicios raros que tiene mucha gente"},
            {"frase": "La envidia al ver las casas de los demás durante el confinamiento"},
            {"frase": "Las crisis existenciales en los tiempos que corren"},
            {"frase": "Quitarse el sujetador cuando llegas a casa"},
            {"frase": "Muchos niños se duermen  en el coche"},
            {"frase": "A una madre nunca se le puede engañar"},
            {"frase": "Llevar braga y sujetador cada uno de un modelo"},
            {"frase": "Todos nos creemos expertos"},
            {"frase": "Que desaparezcan las cosas en casa"},
            {"frase": "El runrún cuando tienes algo pendiente de hacer"},
            {"frase": "Lo odioso que es hacer gestiones con los bancos sin atención al cliente en la oficina"},
            {"frase": "La desesperación de hacer gestiones con empresas por teléfono"},
            {"frase": "Cambiarte de fila en las cajas de los supermercados"},
            {"frase": "Como no sabes qué ponerte al final no sales"},
            {"frase": "Estás irascible porque tienes la regla"},
            {"frase": "Los niños tienen mil juguetes y acaban jugando con lo más simple"},
            {"frase": "El bigotillo de la pubertad"},
            {"frase": "Los niños quieren pasar más tiempo con sus padres"},
            {"frase": "¿Y si fuera millonario?"},
            {"frase": "¿Conocemos bien a nuestra familia?"},
            {"frase": "Dar forma y tacto a mis ideas creativas"},
            {"frase": "Jugar como antes es un superpoder"},
            {"frase": "La nueva paternidad no está reñida con el afecto"},
            {"frase": "Somos lo que vemos"},
            {"frase": "Me gusto tal y como soy"},
            {"frase": "Por nada, tengo una nueva. Renovar, sin dolor"},
            {"frase": "Lo importante es intentarlo, el camino, participar"},
            {"frase": "Cuando intento dejar de fumar, me transformo en la peor versión de mí mismo"},
            {"frase": "Pensar diferente conduce al éxito"},
            {"frase": "Los coches alemanes son los mejores"},
            {"frase": "El fútbol mejor sin interrupciones"},
            {"frase": "Con rebozado de Cheetos todo mejoraría. Mi sabor favorito en otras comidas"},
            {"frase": "Mi momento café"},
            {"frase": "Hacerme con el look de mi mejor amiga"},
            {"frase": "Lo que visto, expresa cómo soy"},
            {"frase": "La gente es única. A mi bola"},
            {"frase": "Mis uñitas, siempre perfectas"},
            {"frase": "Voy a googlear. Con google, mejor"},
            {"frase": "Necesito una solución de movilidad"},
            {"frase": "La cerveza de aquí"},
            {"frase": "La última papita frita sabe mejor"},
            {"frase": "No importa quién eres, lo que importa es lo que haces"},
            {"frase": "Menos consumo más planeta"},
            {"frase": "Si algo es más grande, es mejor"},
            {"frase": "En una cena el anfitrión siempre come el plato frío"},
            {"frase": "Pienso distinto, puedo cambiar la historia"},
            {"frase": "Los lunes son más difíciles de asimilar"},
            {"frase": "Ropa demasiado sucia para el armario y demasiado limpia para la lavadora: bienvenida a la silla"},
            {"frase": "Las despedidas telefónicas con tu madre acaban en \"venga, adiós, valeeee, nos vemos, veeenga, un beso, adiós\""},
            {"frase": "Eres oficialmente adulto si tienes en casa una bolsa llena de otras bolsas"}
          ]
        },
        {
          "is-insight": false,
          "insights": [
            {"frase": "Queremos gustar a la gente"},
            {"frase": "Nos gusta comer bien"},
            {"frase": "La vida es fugaz"},
            {"frase": "El amor es lo más importante"},
            {"frase": "Siempre nos falta tiempo"},
            {"frase": "Tu creatividad no tiene límites"},
            {"frase": "Tu salud es tu riqueza"},
            {"frase": "Queremos sentirnos bien, buscamos experiencias que nos mantengan saludables y felices"},
            {"frase": "La comida rápida y saludable es clave"},
            {"frase": "Amigos auténticos son un tesoro"},
            {"frase": "Los lunes empiezan la semana"},
            {"frase": "Conectados contigo"},
            {"frase": "Las personas quieren sentirse bien"},
            {"frase": "Creemos en la innovación constante"},
            {"frase": "Sé tú mismo"},
            {"frase": "Amo a los perros"},
            {"frase": "Amor es apoyo, confianza y felicidad juntos"}
          ]
        }
      ],
    "retos": [
        {
            "tipo": "Encuentra un insight para...",
            "retos": [
                {"frase": "Los lunes", "autor": ""},
                {"frase": "El primer café del día", "autor": ""},
                {"frase": "El otoño", "autor": ""},
                {"frase": "Una empresa de viajes especializada en viajes de aventuras", "autor": ""},
                {"frase": "Vida universitaria", "autor": ""},
                {"frase": "Boda", "autor": ""},
                {"frase": "Menor en primaria", "autor": ""},
                {"frase": "Viuda harta", "autor": ""},
                {"frase": "Viuda alegre", "autor": ""},
                {"frase": "Adolescente buscando", "autor": ""},
                {"frase": "Profesorado quemado", "autor": ""},
                {"frase": "La hoja en blanco", "autor": ""},
                {"frase": "La sombra", "autor": ""},
                {"frase": "La resaca", "autor": ""},
                {"frase": "La siesta", "autor": ""},
                {"frase": "Mañanas", "autor": ""},
                {"frase": "Redes sociales", "autor": ""}
            ]
        },
        {
            "tipo": "Crea y cuenta la historia de los siguientes personajes...",
            "retos": [
                {"frase": "Una cebolla", "autor": ""},
                {"frase": "¿Por qué el pollo cruzó la carretera?", "autor": ""},
                {"frase": "Un adolescente indignado", "autor": ""}
            ]
        }
    ]
}
